pyscos2000/__init__.py
pyscos2000/browser.py
pyscos2000/checker.py
pyscos2000/concrete.py
pyscos2000/instance.py
pyscos2000/parametertypes.py
pyscos2000/reporter.py
pyscos2000/schema.py
pyscos2000/scos2000.py
pyscos2000/shared.py
pyscos2000/synthetic.py
pyscos2000/version.py
pyscos2000-0.3.0.dist-info/LICENSE
pyscos2000-0.3.0.dist-info/METADATA
pyscos2000-0.3.0.dist-info/WHEEL
pyscos2000-0.3.0.dist-info/entry_points.txt
pyscos2000-0.3.0.dist-info/top_level.txt
pyscos2000-0.3.0.dist-info/RECORD
