Metadata-Version: 2.1
Name: pyscos2000
Version: 0.3.0
Summary: Python SCOS-2000 parsing and checking
Home-page: https://gitlab.irf.se/irf/pyscos2000
Author: Robert Labudda
Author-email: robert.labudda@irf.se
License: MIT
Keywords: SCOS-2000,ESA
Classifier: Intended Audience :: Developers
Classifier: License :: OSI Approved :: MIT License
Classifier: Programming Language :: Python
Classifier: Programming Language :: Python :: 3.6
Classifier: Programming Language :: Python :: 3.7
Classifier: Programming Language :: Python :: 3.8
Classifier: Programming Language :: Python :: 3.9
Classifier: Programming Language :: Python :: 3.10
Requires-Python: >=3.6
License-File: LICENSE
Provides-Extra: docs
Requires-Dist: sphinx ; extra == 'docs'
Requires-Dist: numpydoc ; extra == 'docs'
Requires-Dist: m2r2 ; extra == 'docs'
